Metadata-Version: 2.1
Name: mvpa
Version: 1.0.0
Summary: Multi-voxel pattern analysis (MVPA) tool for fMRI data
Home-page: https://github.com/shobrook/mvpa
Author: shobrook
Author-email: shobrookj@gmail.com
License: MIT
Keywords: mvpa,fmri,correlation
Platform: UNKNOWN
Requires-Python: >=3
